pycatfile.py
pycatfile-0.27.4.data/scripts/catfile.py
pycatfile-0.27.4.dist-info/licenses/LICENSE
pycatfile-0.27.4.dist-info/METADATA
pycatfile-0.27.4.dist-info/WHEEL
pycatfile-0.27.4.dist-info/top_level.txt
pycatfile-0.27.4.dist-info/zip-safe
pycatfile-0.27.4.dist-info/RECORD
