Metadata-Version: 2.4
Name: PyCatFile
Version: 0.27.4
Summary: A tar like file format name archivefile.
Home-page: https://github.com/GameMaker2k/PyCatFile
Download-URL: https://github.com/GameMaker2k/PyCatFile/archive/master.tar.gz
Author: Kazuhana Neko-chan
Author-email: Kazuhika Kitsune-chan <kazuki.suzuki.fox@gmail.com>, Kazuhana Neko-chan <kazuki.suzuki.cat@gmail.com>, Kazuki Neko-kun <kazuki.suzuki.wa@gmail.com>, Kazuki Suzuki Neko-kun <kazuki.suzuki.sadeghi@gmail.com>, Game Maker 2k <gamemaker2k@gmail.com>
Maintainer: Kazuhika Kitsune-chan
Maintainer-email: kazuki.suzuki.fox@gmail.com
License: BSD-3-Clause
Platform: OS Independent
License-File: LICENSE
Dynamic: author
Dynamic: download-url
Dynamic: home-page
Dynamic: license-file
Dynamic: maintainer
Dynamic: maintainer-email
Dynamic: platform
